cppzarr/__init__.py
cppzarr/cppzarr.cp310-win_amd64.pyd
cppzarr/cppzarrwrappers.py
cppzarr/libcppZarr.dll
cpp_zarr-1.1.1.dist-info/METADATA
cpp_zarr-1.1.1.dist-info/WHEEL
cpp_zarr-1.1.1.dist-info/top_level.txt
cpp_zarr-1.1.1.dist-info/RECORD
