Metadata-Version: 2.1
Name: cpp-zarr
Version: 1.1.1
Summary: Python wrappers for cpp-zarr
Home-page: https://github.com/abcucberkeley/cpp-zarr
Author: Matthew Mueller
Author-email: matthewmueller@berkeley.edu
Classifier: Programming Language :: Python :: 3
Classifier: Operating System :: OS Independent
Requires-Python: >=3.8, <3.14
Requires-Dist: numpy >=1.20
